{"data":{"doc":{"path":"/docs/pagination","title":"Paginated queries","content":"<h1 id=\"paginated-queries\"><a href=\"#paginated-queries\" aria-hidden=\"true\">#</a>Paginated queries</h1>\n<p>Use the <code class=\"language-text\">@paginate</code> directive in your GraphQL query to add automatic pagination for a list of source nodes. The query will receive a <code class=\"language-text\">$page: Int</code> variable you can use to load sources for a specific page. Default nodes per page is <code class=\"language-text\">25</code>.</p>\n<h2 id=\"paginated-collections\"><a href=\"#paginated-collections\" aria-hidden=\"true\">#</a>Paginated collections</h2>\n<p>Place the <code class=\"language-text\">@paginate</code> directive after the collection you want to paginate.</p>\n<pre class=\"language-graphql\"><span class=\"token keyword\">query</span> Blog<span class=\"token punctuation\">(</span><span class=\"token variable\">$page</span><span class=\"token punctuation\">:</span> Int<span class=\"token punctuation\">)</span> <span class=\"token punctuation\">{</span>\n  allBlogPost<span class=\"token punctuation\">(</span><span class=\"token attr-name\">perPage</span><span class=\"token punctuation\">:</span> <span class=\"token number\">10</span><span class=\"token punctuation\">,</span> <span class=\"token attr-name\">page</span><span class=\"token punctuation\">:</span> <span class=\"token variable\">$page</span><span class=\"token punctuation\">)</span> <span class=\"token directive function\">@paginate</span> <span class=\"token punctuation\">{</span>\n    pageInfo <span class=\"token punctuation\">{</span>\n      totalPages\n      currentPage\n    <span class=\"token punctuation\">}</span>\n    edges <span class=\"token punctuation\">{</span>\n      node <span class=\"token punctuation\">{</span>\n        id\n        title\n        path\n      <span class=\"token punctuation\">}</span>\n    <span class=\"token punctuation\">}</span>\n  <span class=\"token punctuation\">}</span>\n<span class=\"token punctuation\">}</span></pre>\n<h2 id=\"paginated-taxonomy-pages\"><a href=\"#paginated-taxonomy-pages\" aria-hidden=\"true\">#</a>Paginated taxonomy pages</h2>\n<p>Place the <code class=\"language-text\">@paginate</code> directive after the <code class=\"language-text\">belongsTo</code> field you want to paginate.</p>\n<pre class=\"language-graphql\"><span class=\"token keyword\">query</span> Category<span class=\"token punctuation\">(</span><span class=\"token variable\">$page</span><span class=\"token punctuation\">:</span> Int<span class=\"token punctuation\">)</span> <span class=\"token punctuation\">{</span>\n  category <span class=\"token punctuation\">{</span>\n    title\n    belongsTo<span class=\"token punctuation\">(</span><span class=\"token attr-name\">perPage</span><span class=\"token punctuation\">:</span> <span class=\"token number\">10</span><span class=\"token punctuation\">,</span> <span class=\"token attr-name\">page</span><span class=\"token punctuation\">:</span> <span class=\"token variable\">$page</span><span class=\"token punctuation\">)</span> <span class=\"token directive function\">@paginate</span> <span class=\"token punctuation\">{</span>\n      pageInfo <span class=\"token punctuation\">{</span>\n        totalPages\n        currentPage\n      <span class=\"token punctuation\">}</span>\n      edges <span class=\"token punctuation\">{</span>\n        node <span class=\"token punctuation\">{</span>\n          <span class=\"token operator\">...</span> <span class=\"token keyword\">on</span> Post <span class=\"token punctuation\">{</span>\n            id\n            title\n            path\n          <span class=\"token punctuation\">}</span>\n        <span class=\"token punctuation\">}</span>\n      <span class=\"token punctuation\">}</span>\n    <span class=\"token punctuation\">}</span>\n  <span class=\"token punctuation\">}</span>\n<span class=\"token punctuation\">}</span></pre>\n<h2 id=\"pager-component\"><a href=\"#pager-component\" aria-hidden=\"true\">#</a>Pager component</h2>\n<p>Gridsome has a built-in <code class=\"language-text\">Pager</code> component for easy pagination. Import it from <code class=\"language-text\">gridsome</code> in our components to use it. The component needs at least the <code class=\"language-text\">pageInfo.totalPages</code> and <code class=\"language-text\">pageInfo.currentPage</code> fields to render correctly.</p>\n<h4 id=\"example-usage\"><a href=\"#example-usage\" aria-hidden=\"true\">#</a>Example usage</h4>\n<pre class=\"language-html\"><span class=\"token tag\"><span class=\"token tag\"><span class=\"token punctuation\">&lt;</span>template</span><span class=\"token punctuation\">></span></span>\n  <span class=\"token tag\"><span class=\"token tag\"><span class=\"token punctuation\">&lt;</span>Layout</span><span class=\"token punctuation\">></span></span>\n    <span class=\"token tag\"><span class=\"token tag\"><span class=\"token punctuation\">&lt;</span>ul</span><span class=\"token punctuation\">></span></span>\n      <span class=\"token tag\"><span class=\"token tag\"><span class=\"token punctuation\">&lt;</span>li</span> <span class=\"token attr-name\">v-for</span><span class=\"token attr-value\"><span class=\"token punctuation\">=</span><span class=\"token punctuation\">\"</span>edge in $page.allBlogPost.edges<span class=\"token punctuation\">\"</span></span> <span class=\"token attr-name\">:key</span><span class=\"token attr-value\"><span class=\"token punctuation\">=</span><span class=\"token punctuation\">\"</span>edge.node.id<span class=\"token punctuation\">\"</span></span><span class=\"token punctuation\">></span></span>\n        {{ edge.node.title }}\n      <span class=\"token tag\"><span class=\"token tag\"><span class=\"token punctuation\">&lt;/</span>li</span><span class=\"token punctuation\">></span></span>\n    <span class=\"token tag\"><span class=\"token tag\"><span class=\"token punctuation\">&lt;/</span>ul</span><span class=\"token punctuation\">></span></span>\n    <span class=\"token tag\"><span class=\"token tag\"><span class=\"token punctuation\">&lt;</span>Pager</span> <span class=\"token attr-name\">:info</span><span class=\"token attr-value\"><span class=\"token punctuation\">=</span><span class=\"token punctuation\">\"</span>$page.allBlogPost.pageInfo<span class=\"token punctuation\">\"</span></span><span class=\"token punctuation\">/></span></span>\n  <span class=\"token tag\"><span class=\"token tag\"><span class=\"token punctuation\">&lt;/</span>Layout</span><span class=\"token punctuation\">></span></span>\n<span class=\"token tag\"><span class=\"token tag\"><span class=\"token punctuation\">&lt;/</span>template</span><span class=\"token punctuation\">></span></span>\n\n<span class=\"token tag\"><span class=\"token tag\"><span class=\"token punctuation\">&lt;</span>script</span><span class=\"token punctuation\">></span></span><span class=\"token script language-javascript\">\n<span class=\"token keyword\">import</span> <span class=\"token punctuation\">{</span> Pager <span class=\"token punctuation\">}</span> <span class=\"token keyword\">from</span> <span class=\"token string\">'gridsome'</span>\n\n<span class=\"token keyword\">export</span> <span class=\"token keyword\">default</span> <span class=\"token punctuation\">{</span>\n  components<span class=\"token punctuation\">:</span> <span class=\"token punctuation\">{</span>\n    Pager\n  <span class=\"token punctuation\">}</span>\n<span class=\"token punctuation\">}</span>\n</span><span class=\"token tag\"><span class=\"token tag\"><span class=\"token punctuation\">&lt;/</span>script</span><span class=\"token punctuation\">></span></span>\n\n<span class=\"token tag\"><span class=\"token tag\"><span class=\"token punctuation\">&lt;</span>page-query</span><span class=\"token punctuation\">></span></span><span class=\"token graphql\">\n<span class=\"token keyword\">query</span> Blog<span class=\"token punctuation\">(</span><span class=\"token variable\">$page</span><span class=\"token punctuation\">:</span> Int<span class=\"token punctuation\">)</span> <span class=\"token punctuation\">{</span>\n  allBlogPost<span class=\"token punctuation\">(</span><span class=\"token attr-name\">perPage</span><span class=\"token punctuation\">:</span> <span class=\"token number\">10</span><span class=\"token punctuation\">,</span> <span class=\"token attr-name\">page</span><span class=\"token punctuation\">:</span> <span class=\"token variable\">$page</span><span class=\"token punctuation\">)</span> <span class=\"token directive function\">@paginate</span> <span class=\"token punctuation\">{</span>\n    pageInfo <span class=\"token punctuation\">{</span>\n      totalPages\n      currentPage\n    <span class=\"token punctuation\">}</span>\n    edges <span class=\"token punctuation\">{</span>\n      node <span class=\"token punctuation\">{</span>\n        id\n        title\n      <span class=\"token punctuation\">}</span>\n    <span class=\"token punctuation\">}</span>\n  <span class=\"token punctuation\">}</span>\n<span class=\"token punctuation\">}</span>\n</span><span class=\"token tag\"><span class=\"token tag\"><span class=\"token punctuation\">&lt;/</span>page-query</span><span class=\"token punctuation\">></span></span></pre>\n<table>\n<thead>\n<tr>\n<th>Property</th>\n<th>Default</th>\n<th></th>\n</tr>\n</thead>\n<tbody>\n<tr>\n<td>info</td>\n<td><em>required</em></td>\n<td>Page info from GraphQL result with <em>totalPages</em></td>\n</tr>\n<tr>\n<td>showLinks</td>\n<td>true</td>\n<td>Show navigation links</td>\n</tr>\n<tr>\n<td>showNavigation</td>\n<td>true</td>\n<td>Show previous and next links</td>\n</tr>\n<tr>\n<td>range</td>\n<td>5</td>\n<td>How many links to show</td>\n</tr>\n<tr>\n<td>linkClass</td>\n<td></td>\n<td>Add custom classes to the links</td>\n</tr>\n<tr>\n<td>firstLabel</td>\n<td>«</td>\n<td></td>\n</tr>\n<tr>\n<td>prevLabel</td>\n<td>‹</td>\n<td></td>\n</tr>\n<tr>\n<td>nextLabel</td>\n<td>›</td>\n<td></td>\n</tr>\n<tr>\n<td>lastLabel</td>\n<td>»</td>\n<td></td>\n</tr>\n<tr>\n<td>ariaLabel</td>\n<td>Pagination Navigation</td>\n<td></td>\n</tr>\n<tr>\n<td>ariaLinkLabel</td>\n<td>Go to page %n</td>\n<td></td>\n</tr>\n<tr>\n<td>ariaFirstLabel</td>\n<td>Go to first page</td>\n<td></td>\n</tr>\n<tr>\n<td>ariaCurrentLabel</td>\n<td>Current page. Page %n</td>\n<td></td>\n</tr>\n<tr>\n<td>ariaPrevLabel</td>\n<td>Go to previous page. Page %n</td>\n<td></td>\n</tr>\n<tr>\n<td>ariaNextLabel</td>\n<td>Go to next page. Page %n</td>\n<td></td>\n</tr>\n<tr>\n<td>ariaLastLabel</td>\n<td>Go to last page. Page %n</td>\n<td></td>\n</tr>\n</tbody>\n</table>\n","headings":[{"value":"Paginated queries"}],"subtitles":[{"value":"Paginated collections","anchor":"#paginated-collections"},{"value":"Paginated taxonomy pages","anchor":"#paginated-taxonomy-pages"},{"value":"Pager component","anchor":"#pager-component"}]}},"context":{}}